Metadata-Version: 2.1
Name: database_creator
Version: 1.0
Summary: This repository contains a powerful and easy-to-use library for working with SQLite3 databases in your projects. With this library, you can perform various database operations like creating tables, inserting data, querying data, and updating data with just a few lines of code.
Author-email: hirikayato@mail.ru
